MANIFEST.in
README.rst
setup.py
lambdaskill/__init__.py
lambdaskill/audio.py
lambdaskill/image.py
lambdaskill/model.py
lambdaskill/persist.py
lambdaskill/skill.py
lambdaskill/ssml.py
lambdaskill/utils.py
lambdaskill.egg-info/PKG-INFO
lambdaskill.egg-info/SOURCES.txt
lambdaskill.egg-info/dependency_links.txt
lambdaskill.egg-info/requires.txt
lambdaskill.egg-info/top_level.txt
lambdaskill.egg-info/zip-safe