Metadata-Version: 1.1
Name: lambdaskill
Version: 0.15.0
Summary: A simple toolkit for building Alexa skills.
Home-page: https://github.com/michaeluhl/lambdaskill
Author: Michael Uhl
Author-email: UNKNOWN
License: LGPL
Platform: UNKNOWN
Classifier: Development Status :: 4 - Beta
Classifier: Environment :: Other Environment
Classifier: Intended Audience :: Developers
Classifier: License :: OSI Approved :: GNU Lesser General Public License v3 (LGPLv3)
Classifier: Operating System :: OS Independent
Classifier: Programming Language :: Python :: 3 :: Only
Classifier: Topic :: Software Development :: Libraries :: Application Frameworks
